.gitignore
CHANGELOG.md
README.md
setup.py
examples/example_1.py
examples/example_2.py
examples/example_3.py
examples/example_4.py
examples/example_5.py
examples/untappd.xlsx
imgs/img0.jpg
imgs/img1.png
imgs/img2.jpg
imgs/img3.jpg
untappdscr/__init__.py
untappdscr.egg-info/PKG-INFO
untappdscr.egg-info/SOURCES.txt
untappdscr.egg-info/dependency_links.txt
untappdscr.egg-info/requires.txt
untappdscr.egg-info/top_level.txt